{
 "aggregate_function_based_on": "",
 "color": "#CB2929",
 "creation": "2025-12-06 00:00:00",
 "docstatus": 0,
 "doctype": "Number Card",
 "document_type": "Driver Payment",
 "dynamic_filters_json": "[]",
 "filters_json": "[]",
 "function": "Count",
 "idx": 0,
 "is_public": 1,
 "is_standard": 1,
 "label": "Pending Payments",
 "method": "safarwaala.api.dashboard_metrics.get_driver_pending_balance",
 "modified": "2025-12-06 00:38:52.210411",
 "modified_by": "Administrator",
 "module": "Safarwaala",
 "name": "Driver Pending Payments",
 "owner": "Administrator",
 "parent_document_type": "",
 "show_full_number": 0,
 "show_percentage_stats": 0,
 "stats_time_interval": "Monthly",
 "type": "Custom"
}